liberal_alpha/__init__.py
liberal_alpha/client.py
liberal_alpha/config.py
liberal_alpha/crypto.py
liberal_alpha/exceptions.py
liberal_alpha/proto_utils.py
liberal_alpha/subscriber.py
liberal_alpha/utils.py
liberal_alpha/proto/__init__.py
liberal_alpha/proto/data_entry_pb2.py
liberal_alpha/proto/service_pb2.py
liberal_alpha/proto/service_pb2_grpc.py
liberal_alpha-0.1.17.dist-info/METADATA
liberal_alpha-0.1.17.dist-info/WHEEL
liberal_alpha-0.1.17.dist-info/entry_points.txt
liberal_alpha-0.1.17.dist-info/top_level.txt
liberal_alpha-0.1.17.dist-info/RECORD
