Metadata-Version: 2.1
Name: liberal-alpha
Version: 0.1.17
Summary: Liberal Alpha Python SDK for interacting with gRPC-based backend
Home-page: https://github.com/capybaralabs-xyz/Liberal_Alpha
Author: capybaralabs
Author-email: donny@capybaralabs.xyz
Classifier: Programming Language :: Python :: 3
Classifier: Programming Language :: Python :: 3.7
Classifier: Programming Language :: Python :: 3.8
Classifier: Programming Language :: Python :: 3.9
Classifier: Programming Language :: Python :: 3.10
Classifier: License :: OSI Approved :: MIT License
Classifier: Operating System :: OS Independent
Requires-Python: >=3.8
Requires-Dist: grpcio >=1.30.0
Requires-Dist: protobuf >=5.29.0
Requires-Dist: requests >=2.20.0
Requires-Dist: coincurve >=13.0.0
Requires-Dist: pycryptodome >=3.9.0
Requires-Dist: eth-account >=0.5.0
Requires-Dist: eth-keys >=0.3.0
Requires-Dist: websockets >=8.0.0
Requires-Dist: msgpack >=1.0.0
